hinglish_stopwords/__init__.py
hinglish_stopwords/stopwords.py
hinglish_stopwords/utils.py
hinglish_stopword-0.1.1.dist-info/LICENSE
hinglish_stopword-0.1.1.dist-info/METADATA
hinglish_stopword-0.1.1.dist-info/WHEEL
hinglish_stopword-0.1.1.dist-info/top_level.txt
hinglish_stopword-0.1.1.dist-info/RECORD
