Metadata-Version: 2.1
Name: hinglish_stopword
Version: 0.1.1
Summary: A simple library to filter hinglish stopwords from text.
Author: abhiruchipatilbhagat
Author-email: abhipatilngp@gmail.com
Classifier: Programming Language :: Python :: 3
Classifier: License :: OSI Approved :: MIT License
Classifier: Operating System :: OS Independent
Requires-Python: >=3.6
License-File: LICENSE
